{
	"credit": "Made with Blockbench",
	"texture_size": [94, 65],
	"textures": {
		"1": "iceandfire:item/skulls/ice_skeleton_5",
		"particle": "iceandfire:item/skulls/ice_skeleton_5"
	},
	"elements": [
		{
			"name": "skull",
			"from": [5, 13, -2],
			"to": [15, 21, 6],
			"faces": {
				"north": {"uv": [2.21277, 10.58462, 3.9149, 12.55385], "texture": "#1"},
				"east": {"uv": [0.85107, 10.58462, 2.21277, 12.55385], "texture": "#1"},
				"south": {"uv": [5.2766, 10.58462, 6.97873, 12.55385], "texture": "#1"},
				"west": {"uv": [3.9149, 10.58462, 5.2766, 12.55385], "texture": "#1"},
				"up": {"uv": [2.21277, 8.61539, 3.9149, 10.58462], "texture": "#1"},
				"down": {"uv": [3.9149, 8.61539, 5.61702, 10.58462], "texture": "#1"}
			}
		},
		{
			"name": "beak up",
			"from": [6, 15, -11.5],
			"to": [14, 21, -1.5],
			"faces": {
				"north": {"uv": [3.06383, 6.15385, 4.42553, 7.63077], "texture": "#1"},
				"east": {"uv": [1.3617, 6.15385, 3.06383, 7.63077], "texture": "#1"},
				"south": {"uv": [0, 2.95385, 0.51064, 3.44616], "texture": "#1"},
				"west": {"uv": [4.42553, 6.15385, 6.12766, 7.63077], "texture": "#1"},
				"up": {"uv": [3.06383, 3.69231, 4.42553, 6.15385], "texture": "#1"},
				"down": {"uv": [4.42553, 3.69231, 5.78723, 6.15385], "texture": "#1"}
			}
		},
		{
			"name": "beak down",
			"from": [6.1, 13.25, -11.75],
			"to": [13.9, 15.25, 0.25],
			"rotation": {"angle": 0, "axis": "y", "origin": [9, 13.75, -7]},
			"faces": {
				"north": {"uv": [5.78724, 15.50769, 7.14893, 16], "texture": "#1"},
				"east": {"uv": [3.40426, 15.50769, 5.44681, 16], "texture": "#1"},
				"south": {"uv": [7.82979, 14.03077, 9.19149, 14.52308], "texture": "#1"},
				"west": {"uv": [7.14893, 15.50769, 9.19149, 16], "texture": "#1"},
				"up": {"uv": [5.10639, 12.55384, 6.46808, 15.50769], "texture": "#1"},
				"down": {"uv": [6.46808, 13.04615, 7.48936, 15.50769], "texture": "#1"}
			}
		},
		{
			"name": "teeths 1",
			"from": [5.9, 14.5, -11.76],
			"to": [14.1, 16.5, -1.76],
			"faces": {
				"north": {"uv": [2.5532, 1.47692, 3.91489, 0.98462], "texture": "#1"},
				"east": {"uv": [0.76596, 1.47693, 2.46808, 0.98461], "texture": "#1"},
				"south": {"uv": [0, 2.95385, 0, 2.95385], "texture": "#1"},
				"west": {"uv": [2.46809, 1.47693, 0.76597, 0.98461], "texture": "#1"},
				"up": {"uv": [0, 3.93846, 0.17021, 4.18461], "texture": "#1"},
				"down": {"uv": [0, 5.90769, 0, 5.90769], "texture": "#1"}
			}
		},
		{
			"name": "horn up right",
			"from": [6.5, 16.875, 1.75],
			"to": [8.5, 20.875, 9.75],
			"rotation": {"angle": -22.5, "axis": "y", "origin": [0, 0, 0]},
			"faces": {
				"north": {"uv": [10.21277, 11.56923, 10.55319, 12.55385], "texture": "#1"},
				"east": {"uv": [8.85106, 11.56923, 10.21277, 12.55385], "texture": "#1"},
				"south": {"uv": [11.91489, 11.56923, 12.25532, 12.55385], "texture": "#1"},
				"west": {"uv": [10.55319, 11.56923, 11.91489, 12.55385], "texture": "#1"},
				"up": {"uv": [10.21277, 11.56923, 10.55319, 9.6], "texture": "#1"},
				"down": {"uv": [10.55319, 9.6, 10.89362, 11.56923], "texture": "#1"}
			}
		},
		{
			"name": "horn up left",
			"from": [10, 16.875, 9.75],
			"to": [12, 20.875, 17.75],
			"rotation": {"angle": 22.5, "axis": "y", "origin": [0, 0, 0]},
			"faces": {
				"north": {"uv": [10.21277, 11.56923, 10.55319, 12.55385], "texture": "#1"},
				"east": {"uv": [8.85106, 11.56923, 10.21277, 12.55385], "texture": "#1"},
				"south": {"uv": [11.91489, 11.56923, 12.25532, 12.55385], "texture": "#1"},
				"west": {"uv": [10.55319, 11.56923, 11.91489, 12.55385], "texture": "#1"},
				"up": {"uv": [10.21277, 11.56923, 10.55319, 9.6], "texture": "#1"},
				"down": {"uv": [10.55319, 9.6, 10.89362, 11.56923], "texture": "#1"}
			}
		},
		{
			"name": "horn up left 2",
			"from": [10, 18.75, 16.75],
			"to": [12, 20.75, 22.75],
			"rotation": {"angle": 22.5, "axis": "y", "origin": [0, 0, 0]},
			"faces": {
				"north": {"uv": [13.61702, 3.2, 13.95745, 3.69231], "texture": "#1"},
				"east": {"uv": [12.59574, 3.2, 13.61702, 3.69231], "texture": "#1"},
				"south": {"uv": [14.97872, 3.2, 15.31915, 3.69231], "texture": "#1"},
				"west": {"uv": [13.95745, 3.2, 14.97872, 3.69231], "texture": "#1"},
				"up": {"uv": [13.61702, 3.2, 13.95745, 1.72308], "texture": "#1"},
				"down": {"uv": [13.95745, 1.72308, 14.29787, 3.2], "texture": "#1"}
			}
		},
		{
			"name": "horn up right 2",
			"from": [6.5, 18.75, 8.75],
			"to": [8.5, 20.75, 14.75],
			"rotation": {"angle": -22.5, "axis": "y", "origin": [0, 0, 0]},
			"faces": {
				"north": {"uv": [13.61702, 3.2, 13.95745, 3.69231], "texture": "#1"},
				"east": {"uv": [12.59574, 3.2, 13.61702, 3.69231], "texture": "#1"},
				"south": {"uv": [14.97872, 3.2, 15.31915, 3.69231], "texture": "#1"},
				"west": {"uv": [13.95745, 3.2, 14.97872, 3.69231], "texture": "#1"},
				"up": {"uv": [13.61702, 3.2, 13.95745, 1.72308], "texture": "#1"},
				"down": {"uv": [13.95745, 1.72308, 14.29787, 3.2], "texture": "#1"}
			}
		},
		{
			"name": "horn up left 3",
			"from": [10.1, 18.76, 21.75],
			"to": [11.9, 20.56, 24.75],
			"rotation": {"angle": 22.5, "axis": "y", "origin": [0, 0, 0]},
			"faces": {
				"north": {"uv": [9.87234, 0.98461, 10.21277, 1.47692], "texture": "#1"},
				"east": {"uv": [9.19149, 0.98461, 9.70213, 1.47692], "texture": "#1"},
				"south": {"uv": [15.65957, 0.24615, 16, 0.73846], "texture": "#1"},
				"west": {"uv": [10.38298, 0.98461, 10.89362, 1.47692], "texture": "#1"},
				"up": {"uv": [9.87234, 0.73846, 10.21277, 0], "texture": "#1"},
				"down": {"uv": [10.21277, 0, 10.55319, 0.73846], "texture": "#1"}
			}
		},
		{
			"name": "horn up right 3",
			"from": [6.6, 18.76, 13.75],
			"to": [8.4, 20.56, 16.75],
			"rotation": {"angle": -22.5, "axis": "y", "origin": [0, 0, 0]},
			"faces": {
				"north": {"uv": [9.87234, 0.98461, 10.21277, 1.47692], "texture": "#1"},
				"east": {"uv": [9.19149, 0.98461, 9.70213, 1.47692], "texture": "#1"},
				"south": {"uv": [15.14894, 0, 15.48936, 0.49231], "texture": "#1"},
				"west": {"uv": [10.38298, 0.98461, 10.89362, 1.47692], "texture": "#1"},
				"up": {"uv": [9.87234, 0.73846, 10.21277, 0], "texture": "#1"},
				"down": {"uv": [10.21277, 0, 10.55319, 0.73846], "texture": "#1"}
			}
		},
		{
			"name": "horn down down right",
			"from": [6.25, 14, 0.5],
			"to": [8.25, 16, 8.5],
			"rotation": {"angle": -22.5, "axis": "y", "origin": [0, 0, 0]},
			"faces": {
				"north": {"uv": [9.02127, 7.87692, 9.3617, 8.36923], "texture": "#1"},
				"east": {"uv": [7.65957, 7.87692, 9.02127, 8.36923], "texture": "#1"},
				"south": {"uv": [10.7234, 7.87692, 11.06383, 8.36923], "texture": "#1"},
				"west": {"uv": [9.3617, 7.87692, 10.7234, 8.36923], "texture": "#1"},
				"up": {"uv": [9.02127, 7.87692, 9.3617, 5.90769], "texture": "#1"},
				"down": {"uv": [9.3617, 5.90769, 9.70212, 7.87692], "texture": "#1"}
			}
		},
		{
			"name": "horn down down left",
			"from": [10.25, 14, 8],
			"to": [12.25, 16, 16],
			"rotation": {"angle": 22.5, "axis": "y", "origin": [0, 0, 0]},
			"faces": {
				"north": {"uv": [9.02127, 7.87692, 9.3617, 8.36923], "texture": "#1"},
				"east": {"uv": [7.65957, 7.87692, 9.02127, 8.36923], "texture": "#1"},
				"south": {"uv": [10.7234, 7.87692, 11.06383, 8.36923], "texture": "#1"},
				"west": {"uv": [9.3617, 7.87692, 10.7234, 8.36923], "texture": "#1"},
				"up": {"uv": [9.02127, 7.87692, 9.3617, 5.90769], "texture": "#1"},
				"down": {"uv": [9.3617, 5.90769, 9.70212, 7.87692], "texture": "#1"}
			}
		},
		{
			"name": "horn up right 4",
			"from": [6.35, 14.1, 7.5],
			"to": [8.15, 15.9, 10.5],
			"rotation": {"angle": -22.5, "axis": "y", "origin": [0, 0, 0]},
			"faces": {
				"north": {"uv": [9.87234, 0.98461, 10.21277, 1.47692], "texture": "#1"},
				"east": {"uv": [9.19149, 0.98461, 9.70213, 1.47692], "texture": "#1"},
				"south": {"uv": [15.14894, 0, 15.48936, 0.49231], "texture": "#1"},
				"west": {"uv": [10.38298, 0.98461, 10.89361, 1.47692], "texture": "#1"},
				"up": {"uv": [9.87234, 0.73846, 10.21277, 0], "texture": "#1"},
				"down": {"uv": [10.21277, 0, 10.55319, 0.73846], "texture": "#1"}
			}
		},
		{
			"name": "horn up left 4",
			"from": [10.35, 14.1, 15],
			"to": [12.15, 15.9, 18],
			"rotation": {"angle": 22.5, "axis": "y", "origin": [0, 0, 0]},
			"faces": {
				"north": {"uv": [9.87234, 0.98461, 10.21277, 1.47692], "texture": "#1"},
				"east": {"uv": [9.19149, 0.98461, 9.70213, 1.47692], "texture": "#1"},
				"south": {"uv": [15.65957, 0.24615, 16, 0.73846], "texture": "#1"},
				"west": {"uv": [10.38298, 0.98461, 10.89362, 1.47692], "texture": "#1"},
				"up": {"uv": [9.87234, 0.73846, 10.21277, 0], "texture": "#1"},
				"down": {"uv": [10.21277, 0, 10.55319, 0.73846], "texture": "#1"}
			}
		},
		{
			"name": "horn up up left",
			"from": [11.75, 16, 11],
			"to": [13.75, 18, 19],
			"rotation": {"angle": -22.5, "axis": "x", "origin": [0, 0, 0]},
			"faces": {
				"north": {"uv": [9.02127, 7.87692, 9.3617, 8.36923], "texture": "#1"},
				"east": {"uv": [7.65957, 7.87692, 9.02127, 8.36923], "texture": "#1"},
				"south": {"uv": [10.7234, 7.87692, 11.06383, 8.36923], "texture": "#1"},
				"west": {"uv": [9.3617, 7.87692, 10.7234, 8.36923], "texture": "#1"},
				"up": {"uv": [9.02127, 7.87692, 9.3617, 5.90769], "texture": "#1"},
				"down": {"uv": [9.3617, 5.90769, 9.70212, 7.87692], "texture": "#1"}
			}
		},
		{
			"name": "horn up up left",
			"from": [6.25, 16, 11],
			"to": [8.25, 18, 19],
			"rotation": {"angle": -22.5, "axis": "x", "origin": [0, 0, 0]},
			"faces": {
				"north": {"uv": [9.02127, 7.87692, 9.3617, 8.36923], "texture": "#1"},
				"east": {"uv": [7.65957, 7.87692, 9.02127, 8.36923], "texture": "#1"},
				"south": {"uv": [10.7234, 7.87692, 11.06383, 8.36923], "texture": "#1"},
				"west": {"uv": [9.3617, 7.87692, 10.7234, 8.36923], "texture": "#1"},
				"up": {"uv": [9.02127, 7.87692, 9.3617, 5.90769], "texture": "#1"},
				"down": {"uv": [9.3617, 5.90769, 9.70212, 7.87692], "texture": "#1"}
			}
		},
		{
			"name": "horn up up",
			"from": [6.35, 16.1, 18],
			"to": [8.15, 17.9, 21],
			"rotation": {"angle": -22.5, "axis": "x", "origin": [0, 0, 0]},
			"faces": {
				"north": {"uv": [9.87234, 0.98461, 10.21277, 1.47692], "texture": "#1"},
				"east": {"uv": [9.19149, 0.98461, 9.70213, 1.47692], "texture": "#1"},
				"south": {"uv": [15.14894, 0, 15.48936, 0.49231], "texture": "#1"},
				"west": {"uv": [10.38298, 0.98461, 10.89361, 1.47692], "texture": "#1"},
				"up": {"uv": [9.87234, 0.73846, 10.21277, 0], "texture": "#1"},
				"down": {"uv": [10.21277, 0, 10.55319, 0.73846], "texture": "#1"}
			}
		},
		{
			"name": "horn up up",
			"from": [11.85, 16.1, 18],
			"to": [13.65, 17.9, 21],
			"rotation": {"angle": -22.5, "axis": "x", "origin": [0, 0, 0]},
			"faces": {
				"north": {"uv": [9.87234, 0.98461, 10.21277, 1.47692], "texture": "#1"},
				"east": {"uv": [9.19149, 0.98461, 9.70213, 1.47692], "texture": "#1"},
				"south": {"uv": [15.14894, 0, 15.48936, 0.49231], "texture": "#1"},
				"west": {"uv": [10.38298, 0.98461, 10.89361, 1.47692], "texture": "#1"},
				"up": {"uv": [9.87234, 0.73846, 10.21277, 0], "texture": "#1"},
				"down": {"uv": [10.21277, 0, 10.55319, 0.73846], "texture": "#1"}
			}
		},
		{
			"name": "horn up up",
			"from": [9.125, 20.6, 11],
			"to": [10.925, 22.4, 14],
			"rotation": {"angle": -45, "axis": "x", "origin": [0, 0, 0]},
			"faces": {
				"north": {"uv": [9.87234, 0.98461, 10.21277, 1.47692], "texture": "#1"},
				"east": {"uv": [9.19149, 0.98461, 9.70213, 1.47692], "texture": "#1"},
				"south": {"uv": [15.14894, 0, 15.48936, 0.49231], "texture": "#1"},
				"west": {"uv": [10.38298, 0.98461, 10.89361, 1.47692], "texture": "#1"},
				"up": {"uv": [9.87234, 0.73846, 10.21277, 0], "texture": "#1"},
				"down": {"uv": [10.21277, 0, 10.55319, 0.73846], "texture": "#1"}
			}
		},
		{
			"name": "horn up up left",
			"from": [9, 18.5, 7],
			"to": [11, 22.5, 11],
			"rotation": {"angle": -45, "axis": "x", "origin": [0, 0, 0]},
			"faces": {
				"north": {"uv": [10.7234, 14.76923, 11.06383, 15.75385], "texture": "#1"},
				"east": {"uv": [10.04255, 14.76923, 10.7234, 15.75385], "texture": "#1"},
				"south": {"uv": [11.74468, 14.76923, 12.08511, 15.75385], "texture": "#1"},
				"west": {"uv": [11.06383, 14.76923, 11.74468, 15.75385], "texture": "#1"},
				"up": {"uv": [10.7234, 14.76923, 11.06383, 13.78461], "texture": "#1"},
				"down": {"uv": [11.06383, 13.78461, 11.40425, 14.76923], "texture": "#1"}
			}
		}
	],
	"display": {
		"thirdperson_righthand": {
			"rotation": [75, 0, 0],
			"translation": [-0.75, -0.75, -3.25],
			"scale": [0.4, 0.4, 0.4]
		},
		"thirdperson_lefthand": {
			"rotation": [75, 0, 0],
			"translation": [1, -0.75, -3.25],
			"scale": [0.4, 0.4, 0.4]
		},
		"firstperson_righthand": {
			"rotation": [0, 10, 0],
			"translation": [1, -2.5, 1.25],
			"scale": [0.4, 0.4, 0.4]
		},
		"firstperson_lefthand": {
			"rotation": [0, 10, 0],
			"translation": [3, -3.25, 0],
			"scale": [0.4, 0.4, 0.4]
		},
		"ground": {
			"translation": [0, -1.25, 2.25],
			"scale": [0.4, 0.4, 0.4]
		},
		"gui": {
			"rotation": [30, 225, 0],
			"translation": [0, -3.25, 0],
			"scale": [0.5, 0.5, 0.5]
		},
		"fixed": {
			"rotation": [-36, 0, 0],
			"translation": [-0.75, -4.5, 0.75],
			"scale": [0.75, 0.75, 0.75]
		}
	}
}